{
  "blood": [
    "BloodBag",
    "BloodTypeA+",
    "BloodTypeA-",
    "BloodTypeAb+",
    "BloodTypeAb-",
    "BloodTypeB+",
    "BloodTypeB-",
    "BloodTypeO+",
    "BloodTypeO-",
    "BloodTypeRh+",
    "BloodTypeRh-"
  ],
  "body": [
    "Antibody",
    "Anus",
    "Arm",
    "Bacteria",
    "Bladder",
    "BloodCells",
    "BloodDrop",
    "BloodVessel",
    "Body",
    "Brain",
    "Breasts",
    "CellNuclei",
    "Colon",
    "Dna",
    "Ear",
    "Enzyme",
    "Eye",
    "FemaleReproductiveSystem",
    "Foot",
    "Gallbladder",
    "Head",
    "Heart",
    "Intestine",
    "Joints",
    "Kidneys",
    "Leg",
    "Liver",
    "LiverAlt",
    "Lungs",
    "LymphNode",
    "Mouth",
    "Nerve",
    "Nose",
    "Pancreas",
    "Penis",
    "Penis",
    "Prostate",
    "Skeleton",
    "Skull",
    "Spine",
    "Spleen",
    "Stomach",
    "Testicles",
    "Thyroid",
    "Tissue",
    "Tooth",
    "Tumor",
    "Vagina",
    "Vulva"
  ],
  "conditions": [
    "Allergies",
    "AutoimmuneDisease",
    "BackPain",
    "Burn",
    "CancerousCellNuclei",
    "CervicalCancer",
    "ChemicalBurn",
    "Chills",
    "Chlamydia",
    "Chlamydia",
    "ColorectalCancer",
    "ColorectalCancer",
    "Coughing",
    "Deaf",
    "Diarrhea",
    "DryEyes",
    "DryMouth",
    "Fever",
    "Gonorrhea",
    "Gonorrhea",
    "Headache",
    "Hiv",
    "Hiv",
    "HivInconclusive",
    "HivNegative",
    "HivPositive",
    "Hpv",
    "IntestinalPain",
    "LossOfSmell",
    "LowVision",
    "Lymphoma",
    "Malnutrition",
    "Nausea",
    "OesophagusCancer",
    "Overweight",
    "Pain",
    "PancreaticCancer",
    "Pneumonia",
    "ProstateCancer",
    "SexuallyTransmittedInfection",
    "SkinCancer",
    "StomachCancer",
    "Sweating",
    "Syphilis",
    "ThyroidCancer",
    "Tuberculosis",
    "Underweight",
    "VaricoseVein",
    "ViralLungInfection",
    "Vomiting"
  ],
  "contraceptives": [
    "Contraceptive",
    "ContraceptiveDiaphragm",
    "ContraceptiveInjection",
    "ContraceptivePatch",
    "CopperIntrauterineDevice",
    "FamilyPlanning",
    "FemaleCondom",
    "HormonalRing",
    "Implant",
    "IntrauterineDevice",
    "MaleCondom",
    "OralContraceptive21",
    "OralContraceptive28",
    "Sperm",
    "SyanaPress"
  ],
  "devices": [
    "BedNet",
    "BloodPressureMonitor",
    "BloodPressureMonitorAlt",
    "BreastPump",
    "Cane",
    "Cast",
    "CochlearImplant",
    "ColdTemperature",
    "ContactLens",
    "CpapMachine",
    "CpapMask",
    "CpapMaskAlt",
    "Crutch",
    "CtScan",
    "Defibrillator",
    "DentalHygiene",
    "Ecmo",
    "EndotrachealTube",
    "Eyeglasses",
    "Glucometer",
    "HearingAid",
    "HighTemperature",
    "HospitalBed",
    "HospitalBedAlt",
    "HospitalBedTimer",
    "Hypertension",
    "InfusionPump",
    "Inhaler",
    "IntravenousBag",
    "IntravenousDrip",
    "Laryngoscope",
    "MedicalSample",
    "MedicineContainer",
    "Microscope",
    "MicroscopeWithSpecimen",
    "MobileApp",
    "MortarAndPestle",
    "Odontology",
    "OdontologyImplant",
    "Orthotics",
    "OxygenTank",
    "PatientBand",
    "PatientBandAlt",
    "PpeSanitizerAlt",
    "PpeVirusSanitizerSpray",
    "PulseOximeter",
    "PulseOximeter",
    "Sling",
    "Sonogram",
    "Staples",
    "Stent",
    "Stethoscope",
    "Stitches",
    "SurgicalTools",
    "Syringe",
    "SyringeVaccine",
    "Temperature",
    "TestTube",
    "TestTubes",
    "ThermometerDigital",
    "ToiletPaper",
    "TreatedWater",
    "UltrasoundDevice",
    "UrineSample",
    "Ventilator",
    "VentilatorAlt",
    "VirusLabResearch",
    "VirusLabResearchAlt",
    "WeightScale",
    "Wheelchair",
    "WheelchairAlt",
    "X-ray"
  ],
  "diagnostics": [
    "Biopsy",
    "ConeTestOnNets",
    "ConeTestOnWalls",
    "DiscriminatingConcentrationBioassays",
    "HivSelfTest",
    "IntensityConcentrationBioassays",
    "MalariaMixed",
    "MalariaNegative",
    "MalariaPf",
    "MalariaPv",
    "MalariaTesting",
    "MosquitoCollection",
    "RapidDiagnosticTestingPf",
    "RapidDiagnosticTestingResultInvalid",
    "RapidDiagnosticTestingResultInvalid",
    "RapidDiagnosticTestingResultMixed",
    "RapidDiagnosticTestingResultMixedInvalid",
    "RapidDiagnosticTestingResultMixedInvalid",
    "RapidDiagnosticTestingResultMixedPositve",
    "RapidDiagnosticTestingResultNegative",
    "RapidDiagnosticTestingResultNegative",
    "RapidDiagnosticTestingResultNegative",
    "RapidDiagnosticTestingResultNegativeInvalid",
    "RapidDiagnosticTestingResultNegativeInvalid",
    "RapidDiagnosticTestingResultNoTest",
    "RapidDiagnosticTestingResultPf",
    "RapidDiagnosticTestingResultPfInvalid",
    "RapidDiagnosticTestingResultPfInvalid",
    "RapidDiagnosticTestingResultPositive",
    "RapidDiagnosticTestingResultPv",
    "RapidDiagnosticTestingResultPv",
    "RapidDiagnosticTestingResultPvInvalid",
    "SynergistInsecticideBioassays"
  ],
  "emotions": [
    "Angry",
    "Bandage",
    "Calm",
    "Confused",
    "Coughing",
    "Crying",
    "Dizzy",
    "Expectorate",
    "Fever",
    "Frown",
    "Glasses",
    "Happy",
    "LoudlyCrying",
    "Masked",
    "Measles",
    "Nauseous",
    "Nervous",
    "Neutral",
    "Sad",
    "Sleepy",
    "Smile",
    "Sweating",
    "Tongue",
    "Vomiting",
    "Woozy"
  ],
  "exercise": [
    "ActivityRun",
    "ActivityWalk",
    "ActivityWeights",
    "Exercise",
    "ExerciseBicycle",
    "SupportedWalk",
    "Swimming"
  ],
  "graphs": [
    "BarChart",
    "CuredDecreasingLineChart",
    "CuredIncreasingLineChart",
    "DeathRateDecreasingLineChart",
    "DeathRateIncreasingLineChart",
    "DeathRateStableLineChart",
    "DoubleLineChart",
    "InfectedDecreasingLineChart",
    "InfectedIncreasingLineChart",
    "InfectedStableLineChart",
    "LineChart",
    "PieChart",
    "SplitBarChart"
  ],
  "medications": [
    "BlisterPillsOvalX1",
    "BlisterPillsOvalX14",
    "BlisterPillsOvalX16",
    "BlisterPillsOvalX4",
    "BlisterPillsRoundX1",
    "BlisterPillsRoundX14",
    "BlisterPillsRoundX16",
    "BlisterPillsRoundX4",
    "Medicines",
    "Pill1",
    "Pill2",
    "Pill3",
    "Pill4"
  ],
  "nutrition": [
    "Alcohol",
    "BabyFormula",
    "Carbohydrates",
    "Dairy",
    "DairyFree",
    "Fruits",
    "Gluten",
    "GlutenFree",
    "HotMeal",
    "LowSodium",
    "NoAlcohol",
    "Nutrition",
    "Sodium",
    "Sugar",
    "Sugar",
    "SugarFree",
    "UnhealthyFood",
    "Vegetables"
  ],
  "objects": [
    "Bandage",
    "Calendar",
    "Certificate",
    "Cleaning",
    "Coins",
    "CreditCard",
    "DesktopApp",
    "Hammer",
    "HealthRegisterBook",
    "HealthWorkerForm",
    "InsuranceCard",
    "Justice",
    "Laptop",
    "MedicalBook",
    "Megaphone",
    "MoneyBag",
    "MoneyBills",
    "Phone",
    "Prescription",
    "Spreadsheet",
    "StockOut",
    "StockOutRdt",
    "Trophy",
    "Umbrella",
    "Utensils",
    "WaterTap"
  ],
  "people": [
    "Agriculture",
    "AntenatalCareVisit",
    "Asthma",
    "Baby2-3Months",
    "Baby2-3MonthsAlt",
    "Baby3-6Months",
    "BabyFemale2-3Months",
    "BabyFemale2-3MonthsAlt",
    "BabyFemale3-6Months",
    "BabyMale2-3Months",
    "BabyMale2-3MonthsAlt",
    "BabyMale3-6Months",
    "BusinessPerson",
    "CallCenter",
    "Child1-5Years",
    "Child10-15Years",
    "ChildCare",
    "ChildCognition",
    "ChildFemale10-15Years",
    "Children",
    "CleanHands",
    "CommunityHealthcareWorker",
    "Cpr",
    "Diabetes",
    "Discussion",
    "Doctor",
    "ElderlyMan",
    "ElderlyPeople",
    "ElderlyWoman",
    "EmergencyOperationsPerson",
    "Environmental",
    "FemaleAndMale",
    "Fetus",
    "Fetus24-26Weeks",
    "Fetus32Weeks",
    "Fetus36-38Weeks",
    "Fetus8-12Weeks",
    "Girl1-5Years",
    "Group",
    "GroupDiscussion",
    "Hand",
    "MaleAndFemale",
    "MenWhoHaveSexWithMen",
    "MentalDisorder",
    "Neurosurgery",
    "NursingMother",
    "Outpatient",
    "PediatricSurgery",
    "People",
    "PeopleWhoInjectDrugs",
    "Person",
    "Person",
    "PersonConstructionWorker",
    "PersonDomesticWorker",
    "PersonDomesticWorkerAlt",
    "PersonFactoryWorker",
    "PersonFarmer",
    "PersonFarmerAlt",
    "PersonFemaleDoctor",
    "PersonHealthWorker",
    "PersonMaleDoctor",
    "PersonMilitary",
    "PersonMiner",
    "PersonMinerAlt",
    "PersonNurse",
    "PersonPlantationWorker",
    "PersonPlantationWorkerAlt",
    "PersonPoliceOfficer",
    "PersonPrisoner",
    "PersonSecurityWorker",
    "PersonSurveillanceOfficer",
    "PersonTraveller",
    "PersonTravellerAlt",
    "PersonTruckDriver",
    "Pregnant",
    "RegularPatient",
    "ReproductiveMaternalAndNewbornHealth",
    "SexWorker",
    "SexWorkerFemale",
    "SpeechLanguageTherapy",
    "Spraying",
    "Symptoms",
    "Training",
    "Trauma",
    "WashHands",
    "WaterSanitation",
    "Woman",
    "Yoga",
    "Youth"
  ],
  "places": [
    "Church",
    "City",
    "Clinic",
    "EmergencyOperationsCenter",
    "FieldHospital",
    "Forest",
    "Forest",
    "Home",
    "HomeAlt",
    "HomeWithProperRoof",
    "HomeWithRoofMadeOfPalmBranches",
    "Hospital",
    "Latrine",
    "LatrineAlt",
    "MarketStall",
    "MinistryOfHealth",
    "Mosque",
    "RuralClinic",
    "RuralPostAlt",
    "Temple",
    "TempleAlt",
    "Village"
  ],
  "ppe": [
    "HandWipePaper",
    "PpeApron",
    "PpeDisinfectingWipes",
    "PpeFaceMask",
    "PpeFaceShield",
    "PpeFaceShieldAlt",
    "PpeGloves",
    "PpeGoggles",
    "PpeGown",
    "PpeMaskN95",
    "PpeRespirator",
    "PpeSanitizer",
    "PpeSuit",
    "PpeSurgicalMask"
  ],
  "shapes": [
    "CircleLarge",
    "CircleMedium",
    "CircleSmall",
    "InformationCampaign",
    "SquareLarge",
    "SquareMedium",
    "SquareSmall",
    "StarLarge",
    "StarMedium",
    "StarSmall",
    "TriangleLarge",
    "TriangleLargeInverted",
    "TriangleMedium",
    "TriangleMediumInverted",
    "TriangleSmall",
    "TriangleSmallInverted"
  ],
  "specialties": [
    "AccidentAndEmergency",
    "Admissions",
    "BiochemistryLab",
    "BurnUnit",
    "Cardiology",
    "Chaplaincy",
    "CoronaryCare",
    "CriticalCare",
    "DischargeLounge",
    "EarNoseAndThroat",
    "Endocrinology",
    "Finance",
    "Gastroenterology",
    "Geriatrics",
    "Gym",
    "Gynecology",
    "Hematology",
    "HematologyLab",
    "Hepatology",
    "HumanResources",
    "IntensiveCareUnit",
    "MedicalRecords",
    "Nephrology",
    "Obstetricsmonia",
    "OccupationalTherapy",
    "Oncology",
    "Opthalmology",
    "Orthopaedics",
    "Outpatient",
    "PainManagement",
    "Pediatrics",
    "Pharmacy",
    "PhysicalTherapy",
    "Psychology",
    "Radiology",
    "Respirology",
    "Rheumatology",
    "SocialWork",
    "Sonography",
    "SpeechLanguageTherapy",
    "SurgicalDepartment",
    "Urology",
    "VascularSurgery"
  ],
  "symbols": [
    "AlertCircle",
    "ApprovedDocument",
    "ArmCircumference",
    "ArtificialIntelligence",
    "AssemblyPoint",
    "Award",
    "Biomarker",
    "Biopharma",
    "BloodTransfusion",
    "BodyMassIndex",
    "BreedingSites",
    "CalendarQuarantine",
    "CalendarSchedule",
    "Cancel",
    "Cannabis",
    "Cardiogram",
    "Cardiogram",
    "CardiogramEdit",
    "Chat",
    "Chat",
    "ChatSecure",
    "Checkmark",
    "Cholera",
    "ClinicalDocument",
    "ClinicalRecord",
    "Database",
    "Death",
    "DeathAlt",
    "DeathAlt2",
    "DeniedDocument",
    "Dhis2Logo",
    "Diabetes",
    "Diagnostics",
    "Diaper",
    "Discharge",
    "DocumentEdit",
    "EarNoseAndThroat",
    "Ecology",
    "Electricity",
    "Entry",
    "Exam",
    "ExamMultiple-choice",
    "Excel",
    "FemaleSymbol",
    "Fhir",
    "Fhir2",
    "Fingerprint",
    "GenderSymbols",
    "GlobalPandemic",
    "Globe",
    "GuideDog",
    "Hazardous",
    "HeadCircumference",
    "HealthAlt",
    "HealthDataSecurity",
    "HealthDataSync",
    "HealthIt",
    "HealthLiteracy",
    "HealthShield",
    "Heart",
    "Heartbeat",
    "Height",
    "HighLevel",
    "Hospice",
    "HospitalSymbol",
    "Icd",
    "Icd10",
    "Icd11",
    "Icd9",
    "Imm",
    "Info",
    "InsecticideResistant",
    "IntegratedDataAndResearch",
    "Interoperability",
    "JobLevel",
    "LabSearch",
    "Lactation",
    "LifeScience",
    "Location",
    "Loinc",
    "LowIncome",
    "LowLevel",
    "MagicWand",
    "MagnifyingGlass",
    "MaleSymbol",
    "MedicalAdviceHotline",
    "MedicalSearch",
    "MediumLevel",
    "MentalHealth",
    "Minus",
    "Network2g",
    "Network3g",
    "Network4g",
    "Network5g",
    "NetworkHighBars",
    "NetworkLowBars",
    "NetworkMediumBars",
    "No",
    "NoSmoking",
    "NoSmokingAlt",
    "Notes",
    "Openmrs",
    "Outbreak",
    "OutdoorMeeting",
    "PalliativeCare",
    "PatientVirus",
    "PavedRoad",
    "PavedRoadAlt",
    "Peace",
    "Pharmacy",
    "Pharmacy",
    "Plus",
    "Poison",
    "PolicyGaps",
    "PolicyGapsAlt",
    "Polygon",
    "Preferences",
    "PrescriptionAlt",
    "QrCode",
    "QuarantineHome",
    "Question",
    "QuestionCircle",
    "QuestionTriangle",
    "Referral",
    "ReferralAlt",
    "ResilientAndMigrationSensitiveHealthSystem",
    "RiskAnalysis",
    "Secure",
    "Settings",
    "ShieldVirus",
    "Simple.org",
    "Smoking",
    "SocialDeterminantsOfHealth",
    "SocialDistancing",
    "SocialDistancingAlt",
    "Stop",
    "Support",
    "Tally",
    "Telemedicine",
    "Transgender",
    "UiFamilyFolder",
    "UiFolder",
    "UiMenu",
    "UiMenuGrid",
    "UiUserProfile",
    "UiZoom",
    "UiZoomIn",
    "UiZoomOut",
    "UnpavedRoad",
    "Video",
    "Virus",
    "VirusAlt",
    "VirusMutation",
    "VirusResearch",
    "VirusResearchAlt",
    "WaistCircumference",
    "Warning",
    "WarningTriangle",
    "WaterTap",
    "WaterTreatment"
  ],
  "typography": [
    "0",
    "1",
    "2",
    "3",
    "4",
    "5",
    "6",
    "7",
    "8",
    "9",
    "A",
    "B",
    "C",
    "Cedi",
    "D",
    "DollarSign",
    "E",
    "ExclamationPoint",
    "F",
    "G",
    "H",
    "I",
    "J",
    "K",
    "L",
    "M",
    "N",
    "O",
    "P",
    "Q",
    "QuestionMark",
    "R",
    "Rupee",
    "S",
    "T",
    "U",
    "V",
    "W",
    "X",
    "Y",
    "Yen",
    "Z"
  ],
  "vehicles": [
    "Ambulance",
    "Bicycle",
    "Drone",
    "Helicopter",
    "Machinery",
    "MobileClinic",
    "MotorScooter",
    "Motorcycle",
    "Off-roadMotorcycle",
    "SmallAirplane",
    "Suv",
    "Tank"
  ],
  "zoonoses": [
    "Bat",
    "Chicken",
    "Cow",
    "Donkey",
    "Mosquito",
    "Mosquitos",
    "Pig",
    "Rat",
    "Snake",
    "Spider",
    "Tick"
  ]
}
